operators/__init__.py
operators/operator.py
Operator1-0.1.0.dist-info/METADATA
Operator1-0.1.0.dist-info/WHEEL
Operator1-0.1.0.dist-info/top_level.txt
Operator1-0.1.0.dist-info/RECORD
